<?xml version="1.0" encoding="UTF-8"?>
<!DOCTYPE generatorConfiguration PUBLIC "-//mybatis.org//DTD MyBatis Generator Configuration 1.0//EN" "http://mybatis.org/dtd/mybatis-generator-config_1_0.dtd">

<generatorConfiguration>
    <classPathEntry location="/Users/apple/.m2/repository/mysql/mysql-connector-java/5.1.27/mysql-connector-java-5.1.27.jar"/>
    <context id="MySQLTables" targetRuntime="MyBatis3">
        <property name="javaFormatter" value="org.mybatis.generator.api.dom.DefaultJavaFormatter"/>
        <property name="xmlFormatter" value="org.mybatis.generator.api.dom.DefaultXmlFormatter"/>
        <jdbcConnection driverClass="com.mysql.jdbc.Driver" connectionURL="jdbc:mysql://localhost:3306/member?useUnicode=true&amp;characterEncoding=utf-8" userId="root" password=""/>
        <javaTypeResolver>
            <property name="forceBigDecimals" value="false"/>
        </javaTypeResolver>
        <javaModelGenerator targetPackage="com.member.sys.domain" targetProject="/Users/apple/Documents/develop-git/member/member-dao/src/main/java">
            <property name="enableSubPackages" value="false"/>
            <property name="trimStrings" value="true"/>
        </javaModelGenerator>
        <sqlMapGenerator targetPackage="com.member.sys.dao" targetProject="/Users/apple/Documents/develop-git/member/member-dao/src/main/resources">
            <property name="enableSubPackages" value="false"/>
        </sqlMapGenerator>
        <javaClientGenerator type="XMLMAPPER" targetPackage="com.member.sys.dao" targetProject="/Users/apple/Documents/develop-git/member/member-dao/src/main/java">
            <property name="enableSubPackages" value="false"/>
        </javaClientGenerator>
        <table tableName="sys_consume" domainObjectName="SysConsumeDomain" enableCountByExample="false" enableUpdateByExample="false" enableDeleteByExample="false" enableSelectByExample="false" selectByExampleQueryId="false"/>
    </context>
</generatorConfiguration>
